pypirccua/__init__.py
pypirccua/__main__.py
pypirccua/heatmaprange.py
pypirccua/pidbcard.py
pypirccua/pidbcardlist.py
pypirccua/pidbcardthreaded.py
pypirccua/pidbcardview.py
pypirccua/pirccli.py
pypirccua/pircviewer.py
pypirccua/pitableview.py
pypirccua/data/__init__.py
tests/__init__.py
tests/test_dbcard.py
pypirccua-1.1.0.dist-info/LICENSE
pypirccua-1.1.0.dist-info/METADATA
pypirccua-1.1.0.dist-info/WHEEL
pypirccua-1.1.0.dist-info/entry_points.txt
pypirccua-1.1.0.dist-info/top_level.txt
pypirccua-1.1.0.dist-info/RECORD
