Metadata-Version: 2.1
Name: pypirccua
Version: 1.1.0
Summary: A PyQt-based application for visualizing and analyzing relay counts from DB files.
Home-page: https://github.com/aknavj/pypirccua
Author: Ondrej Vanka
Author-email: ondrej@vanka.net
Classifier: Programming Language :: Python :: 3
Classifier: License :: OSI Approved :: MIT License
Classifier: Operating System :: OS Independent
Requires-Python: >=3.7
License-File: LICENSE
Requires-Dist: PyQt5>=5.15.0
Requires-Dist: matplotlib>=3.3.0
